PyBreathTranscript/__init__.py
PyBreathTranscript/audio_data.pkl
PyBreathTranscript/audio_fingerprinting.py
PyBreathTranscript/references.pkl
PyBreathTranscript/transcript.py
PyBreathTranscript/transcript_dtw.py
PyBreathTranscript/waveform_comparing.py
pybreathtranscript-1.1.0.dist-info/licenses/LICENSE
pybreathtranscript-1.1.0.dist-info/METADATA
pybreathtranscript-1.1.0.dist-info/WHEEL
pybreathtranscript-1.1.0.dist-info/top_level.txt
pybreathtranscript-1.1.0.dist-info/RECORD
