Metadata-Version: 2.4
Name: PyBreathTranscript
Version: 1.1.0
Summary: Tool for transcribing breaths from audio files
Author-email: Ilya Shlom <ilyashlom32@gmail.com>
License-Expression: MIT
Project-URL: Homepage, https://github.com/ilya-shlom/breathing-analysis
Project-URL: Issues, https://github.com/ilya-shlom/breathing-analysis/issues
Keywords: Transcription,Breath,Breathe,Breath transcription
Classifier: Programming Language :: Python :: 3
Classifier: Operating System :: OS Independent
Requires-Python: >=3.11
License-File: LICENSE
Requires-Dist: pydub==0.25.1
Requires-Dist: scikit-learn==1.5.2
Requires-Dist: numpy
Requires-Dist: librosa
Requires-Dist: joblib==1.4.2
Dynamic: license-file
